cobrapy_shim.py
cobrapy_shim-0.1.1.dist-info/METADATA
cobrapy_shim-0.1.1.dist-info/DESCRIPTION.rst
cobrapy_shim-0.1.1.dist-info/top_level.txt
cobrapy_shim-0.1.1.dist-info/metadata.json
cobrapy_shim-0.1.1.dist-info/RECORD
cobrapy_shim-0.1.1.dist-info/WHEEL
cobrapy_shim-0.1.1.dist-info/entry_points.txt
