Metadata-Version: 2.0
Name: cobrapy-shim
Version: 0.1.1
Summary: UNKNOWN
Home-page: https://github.com/opencobra/cobrapy_shim
Author: Ali Ebrahim
Author-email: aebrahim@ucsd.edu
License: CC0
Platform: UNKNOWN
Classifier: Environment :: Console
Classifier: License :: CC0 1.0 Universal (CC0 1.0) Public Domain Dedication
Classifier: Operating System :: OS Independent
Requires-Dist: cobra (>=0.4.0b4)
